{
  "day0": {
    "titles": [
      "Миньоны: Грювитация 2D",
      "Красная Шапочка 2D",
      "Добыча 2D",
      "Дневная смена 2D",
      "Джиперс Криперс: Возрожденный 2D"
    ],
    "seansScedule": {
      "Миньоны: Грювитация 2D": [
        ["10:30", "Миньоны: Грювитация 2D", "6+", 170, 0],
        ["14:15", "Миньоны: Грювитация 2D", "6+", 200, 2]
      ],
      "Красная Шапочка 2D": [
        ["12:15", "Красная Шапочка 2D", "12+", 280, 1],
        ["16:00", "Красная Шапочка 2D", "12+", 320, 3]
      ],
      "Добыча 2D": [["18:00", "Добыча 2D", "16+", 250, 4]],
      "Джиперс Криперс: Возрожденный 2D": [
        ["19:50", "Джиперс Криперс: Возрожденный 2D", "18+", 350, 5]
      ],
      "Дневная смена 2D": [["21:35", "Дневная смена 2D", "16+", 200, 6]]
    }
  },
  "day1": {
    "titles": [
      "Миньоны: Грювитация 2D",
      "Добыча 2D",
      "Чёрный телефон 2D",
      "Джиперс Криперс: Возрожденный 2D"
    ],
    "seansScedule": {
      "Миньоны: Грювитация 2D": [
        ["14:00", "Миньоны: Грювитация 2D", "6+", 150, 0]
      ],
      "is": [["There", "is", "no", "movie", 1]],
      "Чёрный телефон 2D": [["17:45", "Чёрный телефон 2D", "16+", 170, 2]],
      "Добыча 2D": [["19:45", "Добыча 2D", "16+", 200, 3]],
      "Джиперс Криперс: Возрожденный 2D": [
        ["21:35", "Джиперс Криперс: Возрожденный 2D", "18+", 300, 4]
      ]
    }
  },
  "day2": {
    "titles": [
      "Миньоны: Грювитация 2D",
      "Добыча 2D",
      "Чёрный телефон 2D",
      "Джиперс Криперс: Возрожденный 2D"
    ],
    "seansScedule": {
      "Миньоны: Грювитация 2D": [
        ["14:15", "Миньоны: Грювитация 2D", "6+", 150, 0]
      ],
      "Чёрный телефон 2D": [["15:55", "Чёрный телефон 2D", "16+", 150, 1]],
      "Добыча 2D": [
        ["17:55", "Добыча 2D", "16+", 200, 2],
        ["21:30", "Добыча 2D", "16+", 200, 4]
      ],
      "Джиперс Криперс: Возрожденный 2D": [
        ["19:45", "Джиперс Криперс: Возрожденный 2D", "18+", 300, 3]
      ]
    }
  },
  "day3": {
    "titles": [
      "Миньоны: Грювитация 2D",
      "Добыча 2D",
      "Чёрный телефон 2D",
      "Джиперс Криперс: Возрожденный 2D"
    ],
    "seansScedule": {
      "Миньоны: Грювитация 2D": [
        ["14:30", "Миньоны: Грювитация 2D", "6+", 150, 0],
        ["16:10", "Миньоны: Грювитация 2D", "6+", 150, 1]
      ],
      "Джиперс Криперс: Возрожденный 2D": [
        ["17:50", "Джиперс Криперс: Возрожденный 2D", "18+", 300, 2]
      ],
      "Добыча 2D": [["19:35", "Добыча 2D", "16+", 200, 3]],
      "Чёрный телефон 2D": [["21:25", "Чёрный телефон 2D", "16+", 200, 4]]
    }
  },
  "day4": {
    "titles": [
      "Миньоны: Грювитация 2D",
      "Красная Шапочка 2D",
      "Добыча 2D",
      "Джиперс Криперс: Возрожденный 2D"
    ],
    "seansScedule": {
      "Красная Шапочка 2D": [
        ["14:15", "Красная Шапочка 2D", "12+", 230, 0],
        ["17:45", "Красная Шапочка 2D", "12+", 270, 2]
      ],
      "Миньоны: Грювитация 2D": [
        ["16:05", "Миньоны: Грювитация 2D", "6+", 150, 1]
      ],
      "Джиперс Криперс: Возрожденный 2D": [
        ["19:40", "Джиперс Криперс: Возрожденный 2D", "18+", 300, 3]
      ],
      "Добыча 2D": [["21:25", "Добыча 2D", "16+", 200, 4]]
    }
  },
  "day5": {
    "titles": [
      "Миньоны: Грювитация 2D",
      "Красная Шапочка 2D",
      "Добыча 2D",
      "Дневная смена 2D",
      "Джиперс Криперс: Возрожденный 2D"
    ],
    "seansScedule": {
      "Миньоны: Грювитация 2D": [
        ["13:30", "Миньоны: Грювитация 2D", "6+", 150, 0]
      ],
      "Красная Шапочка 2D": [
        ["15:10", "Красная Шапочка 2D", "12+", 250, 1],
        ["18:50", "Красная Шапочка 2D", "12+", 350, 3]
      ],
      "Добыча 2D": [["17:00", "Добыча 2D", "16+", 200, 2]],
      "Дневная смена 2D": [["20:45", "Дневная смена 2D", "16+", 250, 4]],
      "Джиперс Криперс: Возрожденный 2D": [
        ["22:50", "Джиперс Криперс: Возрожденный 2D", "18+", 330, 5]
      ]
    }
  },
  "day6": {
    "titles": [
      "Миньоны: Грювитация 2D",
      "Красная Шапочка 2D",
      "Добыча 2D",
      "Дневная смена 2D",
      "Джиперс Криперс: Возрожденный 2D"
    ],
    "seansScedule": {
      "Миньоны: Грювитация 2D": [
        ["11:00", "Миньоны: Грювитация 2D", "6+", 170, 0],
        ["14:45", "Миньоны: Грювитация 2D", "6+", 200, 2]
      ],
      "Красная Шапочка 2D": [
        ["12:45", "Красная Шапочка 2D", "12+", 280, 1],
        ["16:30", "Красная Шапочка 2D", "12+", 320, 3]
      ],
      "Добыча 2D": [["18:30", "Добыча 2D", "16+", 250, 4]],
      "Дневная смена 2D": [["20:25", "Дневная смена 2D", "16+", 250, 5]],
      "Джиперс Криперс: Возрожденный 2D": [
        ["22:35", "Джиперс Криперс: Возрожденный 2D", "18+", 330, 6]
      ]
    }
  }
}
