{
  "day0": {
    "titles": [
      "Коты Эрмитажа 2D",
      "На солнце, вдоль рядов кукурузы 2D",
      "Поехавшая 2D",
      "Джон Уик 4 2D"
    ],
    "seansScedule": {
      "Коты Эрмитажа 2D": [
        ["10:20", "Коты Эрмитажа 2D", "6+", 220, 0],
        ["12:10", "Коты Эрмитажа 2D", "6+", 300, 1]
      ],
      "На солнце, вдоль рядов кукурузы 2D": [
        ["14:00", "На солнце, вдоль рядов кукурузы 2D", "6+", 350, 2]
      ],
      "Джон Уик 4 2D": [
        ["15:55", "Джон Уик 4 2D", "18+", 370, 3],
        ["21:25", "Джон Уик 4 2D", "18+", 330, 5]
      ],
      "Поехавшая 2D": [["19:10", "Поехавшая 2D", "16+", 370, 4]]
    }
  },
  "day1": {
    "titles": [
      "Коты Эрмитажа 2D",
      "На солнце, вдоль рядов кукурузы 2D",
      "Удача 2D",
      "Поехавшая 2D",
      "Джон Уик 4 2D"
    ],
    "seansScedule": {
      "Коты Эрмитажа 2D": [["10:30", "Коты Эрмитажа 2D", "6+", 180, 0]],
      "Удача 2D": [["12:20", "Удача 2D", "6+", 220, 1]],
      "На солнце, вдоль рядов кукурузы 2D": [
        ["14:25", "На солнце, вдоль рядов кукурузы 2D", "6+", 250, 2]
      ],
      "Поехавшая 2D": [["16:15", "Поехавшая 2D", "16+", 270, 3]],
      "Джон Уик 4 2D": [
        ["18:30", "Джон Уик 4 2D", "18+", "330", 4],
        ["21:40", "Джон Уик 4 2D", "18+", "330", 5]
      ]
    }
  },
  "day2": {
    "titles": [
      "Коты Эрмитажа 2D",
      "На солнце, вдоль рядов кукурузы 2D",
      "Удача 2D",
      "Человек-муравей и Оса: Квантомания 2D",
      "Поехавшая 2D",
      "Джон Уик 4 2D"
    ],
    "seansScedule": {
      "Удача 2D": [["11:00", "Удача 2D", "6+", 180, 0]],
      "Коты Эрмитажа 2D": [["13:05", "Коты Эрмитажа 2D", "6+", 220, 1]],
      "Поехавшая 2D": [["14:55", "Поехавшая 2D", "16+", 250, 2]],
      "Человек-муравей и Оса: Квантомания 2D": [
        ["17:10", "Человек-муравей и Оса: Квантомания 2D", "12+", 270, 3]
      ],
      "На солнце, вдоль рядов кукурузы 2D": [
        ["19:35", "На солнце, вдоль рядов кукурузы 2D", "6+", 300, 4]
      ],
      "Джон Уик 4 2D": [["21:30", "Джон Уик 4 2D", "18+", 330, 5]]
    }
  },
  "day3": {
    "titles": [
      "Коты Эрмитажа 2D",
      "На солнце, вдоль рядов кукурузы 2D",
      "Удача 2D",
      "Человек-муравей и Оса: Квантомания 2D",
      "Поехавшая 2D",
      "Джон Уик 4 2D"
    ],
    "seansScedule": {
      "Коты Эрмитажа 2D": [["10:30", "Коты Эрмитажа 2D", "6+", 180, 0]],
      "Удача 2D": [["12:20", "Удача 2D", "6+", 220, 1]],
      "Человек-муравей и Оса: Квантомания 2D": [
        ["14:25", "Человек-муравей и Оса: Квантомания 2D", "12+", 250, 2]
      ],
      "На солнце, вдоль рядов кукурузы 2D": [
        ["16:50", "На солнце, вдоль рядов кукурузы 2D", "6+", 270, 3]
      ],
      "Джон Уик 4 2D": [["18:45", "Джон Уик 4 2D", "18+", 330, 4]],
      "Поехавшая 2D": [["21:55", "Поехавшая 2D", "16+", 300, 5]]
    }
  },
  "day4": {
    "titles": [
      "Коты Эрмитажа 2D",
      "На солнце, вдоль рядов кукурузы 2D",
      "Удача 2D",
      "Человек-муравей и Оса: Квантомания 2D",
      "Поехавшая 2D",
      "Джон Уик 4 2D"
    ],
    "seansScedule": {
      "Удача 2D": [["11:00", "Удача 2D", "6+", 150, 0]],
      "Коты Эрмитажа 2D": [["13:05", "Коты Эрмитажа 2D", "6+", 220, 1]],
      "Поехавшая 2D": [["14:50", "Поехавшая 2D", "16+", 250, 2]],
      "Человек-муравей и Оса: Квантомания 2D": [
        ["17:05", "Человек-муравей и Оса: Квантомания 2D", "12+", 270, 3]
      ],
      "На солнце, вдоль рядов кукурузы 2D": [
        ["19:30", "На солнце, вдоль рядов кукурузы 2D", "6+", 300, 4]
      ],
      "Джон Уик 4 2D": [["21:25", "Джон Уик 4 2D", "18+", 330, 5]]
    }
  },
  "day5": {
    "titles": [
      "Коты Эрмитажа 2D",
      "На солнце, вдоль рядов кукурузы 2D",
      "Удача 2D",
      "Человек-муравей и Оса: Квантомания 2D",
      "Поехавшая 2D",
      "Джон Уик 4 2D"
    ],
    "seansScedule": {
      "Коты Эрмитажа 2D": [["11:00", "Коты Эрмитажа 2D", "6+", 180, 0]],
      "Удача 2D": [["12:50", "Удача 2D", "6+", 220, 1]],
      "Человек-муравей и Оса: Квантомания 2D": [
        ["14:55", "Человек-муравей и Оса: Квантомания 2D", "12+", 250, 2]
      ],
      "На солнце, вдоль рядов кукурузы 2D": [
        ["17:20", "На солнце, вдоль рядов кукурузы 2D", "6+", 350, 3]
      ],
      "Джон Уик 4 2D": [["19:15", "Джон Уик 4 2D", "18+", 400, 4]],
      "Поехавшая 2D": [["22:30", "Поехавшая 2D", "16+", 370, 5]]
    }
  },
  "day6": {
    "titles": [
      "Коты Эрмитажа 2D",
      "На солнце, вдоль рядов кукурузы 2D",
      "Удача 2D",
      "Поехавшая 2D",
      "Джон Уик 4 2D"
    ],
    "seansScedule": {
      "Коты Эрмитажа 2D": [
        ["10:00", "Коты Эрмитажа 2D", "6+", 220, 0],
        ["13:50", "Коты Эрмитажа 2D", "6+", 320, 2]
      ],
      "Удача 2D": [["11:45", "Удача 2D", "6+", 280, 1]],
      "На солнце, вдоль рядов кукурузы 2D": [
        ["15:40", "На солнце, вдоль рядов кукурузы 2D", "6+", 350, 3]
      ],
      "Поехавшая 2D": [["17:35", "Поехавшая 2D", "16+", 370, 4]],
      "Джон Уик 4 2D": [
        ["20:55", "Джон Уик 4 2D", "18+", 400, 5],
        ["23:10", "Джон Уик 4 2D", "18+", 350, 6]
      ]
    }
  }
}
